tokenizer_viz/__init__.py
tokenizer_viz/visualization.py
tokenizer_viz-0.2.2.dist-info/LICENSE
tokenizer_viz-0.2.2.dist-info/METADATA
tokenizer_viz-0.2.2.dist-info/WHEEL
tokenizer_viz-0.2.2.dist-info/top_level.txt
tokenizer_viz-0.2.2.dist-info/RECORD
