Metadata-Version: 2.1
Name: tokenizer-viz
Version: 0.2.2
Summary: A package to visualize tokenization boundaries using HTML
Home-page: https://github.com/ds08tf/tokenizer-viz
Author: Darien Schettler
Author-email: ds08tf@gmail.com
Classifier: Development Status :: 3 - Alpha
Classifier: Intended Audience :: Developers
Classifier: License :: OSI Approved :: MIT License
Classifier: Programming Language :: Python :: 3
Classifier: Programming Language :: Python :: 3.7
Classifier: Programming Language :: Python :: 3.8
Classifier: Programming Language :: Python :: 3.9
Requires-Python: >=3.7
License-File: LICENSE
Requires-Dist: matplotlib
Requires-Dist: IPython
